<!DOCTYPE verb SYSTEM "verb.dtd">
  <verb>
    <id> 赤裸裸 </id>
    <frameset id="f1">
      <role argnum="0" argrole="thing described"/>
      <frame>
	<mapping>
	  <V/>
	  <mapitem src="sbj" trg="arg0"/>
	</mapping>
	<example>
	  <parse>
	  (NP-PRD (DNP (NP (NN 强权)
			   (NN 政治)
			   (CC 和)
			   (NN 霸权主义))
		       (DEG 的))
		  (QP (ADVP (AD 又))
		      (QP (CD 一)
			  (CLP (M 次))))
		  (CP (WHNP-1 (-NONE- *OP*))
		      (CP (IP (NP-SBJ (-NONE- *T*-1))
			      (VP (VA 赤裸裸)))
			  (DEC 的)))
		  (NP (NN 表现))) 
	  </parse>
	  <arg n="0">
	  *T*-1 
	  </arg>
	  <V/>
	</example>
      </frame>
    </frameset>
  </verb>
