<!DOCTYPE verb SYSTEM "verb.dtd">
<verb>
  <id> 批驳 </id>
  <frameset id="f1">
    <role argnum="0" argrole="agent"/>
    <role argnum="1" argrole="entity arg0 refutes"/>
    <frame>
      <mapping>
	<V/>
	<mapitem src="sbj" trg="arg0"/>
      </mapping>
      <example>
	<parse>
	(IP (NP-SBJ (NN 执政党))
	    (VP (VP (ADVP (AD 未))
		    (VP (VV 能)
			(VP (NP-MNR (ADJP (JJ 严))
				    (NP (NN 词)))
			    (VP (VV 批驳)))))
		(PU ，)
		(VP (ADVP (AD 反而))
		    (VP (VP (VV 因势就导))
			(VP (VV 打)
			    (NP-OBJ (PU 「)
				    (NN 恐惧)
				    (NN 牌)
				    (PU 」))))))) 
	</parse>
	<arg n="0">
	执政党 
	</arg>
	<arg n="m" f="adv">
	严 词 
	</arg>
	<arg n="m" f="adv">
	未 
	</arg>
	<V/>
      </example>
    </frame>
  </frameset>
</verb>
