<!DOCTYPE verb SYSTEM "verb.dtd">
<verb>
  <id> 要紧 </id>
  <frameset id="f1">
    <role argnum="0" argrole="entity described"/>
    <frame>
      <mapping>
	<V/>
	<mapitem src="sbj" trg="arg0"/>
      </mapping>
      <example>
	<parse>
	(IP (IP-TPC (NP-SBJ (-NONE- *PRO*))
		    (VP (VV 做)
			(NP-OBJ (QP (CD 一)
				    (CLP (M 个)))
				(CP (WHNP-1 (-NONE- *OP*))
				    (CP (IP (NP-SBJ (NN 社会)
						    (NN 正义))
					    (VP (MSP 所)
						(VP (VV 期待)
						    (NP-OBJ (-NONE- *T*-1)))))
					(DEC 的)))
				(NP (PU 「)
				    (NN 无冕王)
				    (PU 」)))))
	    (PU ，)
	    (PP-ADV (P 除了)
		    (LCP (IP (NP-SBJ (-NONE- *PRO*))
			     (VP (VV 要)
				 (VP (VE 有)
				     (NP-OBJ (NN 冲劲)
					     (CC 与)
					     (NN 活力)))))
			 (LC 之外)))
	    (PU ，)
	    (NP-SBJ (CP (WHNP-2 (-NONE- *OP*))
			(CP (IP (NP-SBJ (-NONE- *T*-2))
				(VP (ADVP (AD 最))
				    (VP (VA 要紧))))
			    (DEC 的))))
	    (VP (VC 是)
		(NP-PRD (NN 谦虚)))) 
	</parse>
	<arg n="0">
	*T*-2 
	</arg>
	<arg n="m" f="adv">
	最 
	</arg>
	<V/>
      </example>
    </frame>
  </frameset>
</verb>
