<!DOCTYPE verb SYSTEM "verb.dtd">
<verb>
  <id> 热情澎湃 </id>
  <frameset id="f1">
    <role argnum="0" argrole="person described"/>
    <frame>
      <mapping>
	<V/>
	<mapitem src="sbj" trg="arg0"/>
      </mapping>
      <example>
	<parse>
	(IP (NP-SBJ (-NONE- *pro*))
	    (VP (NP-LOC (NP-PN (NR 中正)
			       (NN 纪念堂))
			(NP (NN 广场)))
		(ADVP (AD 却))
		(VP (VV 热情澎湃)))) 
	</parse>
	<arg n="0">
	*pro* 
	</arg>
	<arg n="m" f="adv">
	却 
	</arg>
	<arg n="m" f="loc">
	中正 纪念堂 广场 
	</arg>
	<V/>
      </example>
    </frame>
  </frameset>
</verb>
