<!DOCTYPE verb SYSTEM "verb.dtd">
  <verb>
    <id> 复苏 </id>
    <frameset id="f1">
      <role argnum="0" argrole="theme"/>
      <frame>
	<mapping>
	  <V/>
	  <mapitem src="sbj" trg="arg0"/>
	</mapping>
	<example>
	  <parse>
	  (IP (NP-TMP (NT 明年))
	      (NP-SBJ (DNP (NP (DP (DT 其他))
			       (NP-PN (NR 亚洲))
			       (NP (NN 国家)))
			   (DEG 的))
		      (NP (NN 经济)))
	      (VP (VV 能够)
		  (VP (VV 复苏)))) 
	  </parse>
	  <arg n="0">
	  其他 亚洲 国家 的 经济 
	  </arg>
	  <V/>
	</example>
      </frame>
    </frameset>
  </verb>
