<!DOCTYPE verb SYSTEM "verb.dtd">
  <verb>
    <id> 联盟 </id>
    <frameset id="f1">
      <role argnum="0" argrole="entities forming alliance"/>
      <frame>
	<mapping>
	  <V/>
	  <mapitem src="sbj" trg="arg0"/>
	</mapping>
	<example>
	  <parse>
	  (IP (NP-TMP (NT １９７４年))
	      (PU ，)
	      (NP-SBJ (NN 希族人))
	      (VP (PP-PRP (P 为)
			  (IP (NP-SBJ (-NONE- *PRO*))
			      (VP (VV 寻求)
				  (IP-OBJ (NP-SBJ (-NONE- *PRO*))
					  (VP (PP (P 与)
						  (NP-PN (NR 希腊)))
					      (VP (VV 联盟)))))))
		  (VP (MSP 而)
		      (VP (VV 发动)
			  (NP-OBJ (NN 政变)))))) 
	  </parse>
	  <arg n="0">
	  *PRO* 
	  </arg>
	  <arg n="0">
	  与 希腊 
	  </arg>
	  <V/>
	</example>
      </frame>
    </frameset>
  </verb>
