<!DOCTYPE verb SYSTEM "verb.dtd">
  <verb>
    <id> 小觑 </id>
    <frameset id="f1">
      <role argnum="0" argrole="people described"/>
      <role argnum="1" argrole="entity arg0 looks down upon"/>
      <frame>
	<mapping>
	  <V/>
	  <mapitem src="sbj" trg="arg1"/>
	</mapping>
	<example>
	  <parse>
	  (IP (IP-CND (NP-SBJ (NN 大陆))
		      (VP (ADVP (CS 若))
			  (VP (VC 是)
			      (VP (PP-PRP (P 因为)
					  (IP (NP-SBJ (-NONE- *PRO*))
					      (VP (VV 坚守)
						  (NP-OBJ (NN 人民币)
							  (NN 汇率)))))
				  (VP (MSP 而)
				      (VP (VV 丧失)
					  (NP-OBJ (NN 出口)
						  (NN 竞争)
						  (NN 优势))))))))
	      (PU ，)
	      (IP-ADV (NP-SBJ (-NONE- *PRO*))
		      (VP (PP-DIR (P 对於)
				  (NP (QP (CD 成千上万)
					  (CLP (M 家)))
				      (PU 、)
				      (CP (WHNP-1 (-NONE- *OP*))
					  (CP (IP (NP-SBJ (-NONE- *T*-1))
						  (VP (VV 仰赖)
						      (NP-OBJ (NN 大陆))
						      (IP (NP-SBJ (-NONE- *PRO*))
							  (VP (VC 为)
							      (NP-PRD (ADJP (ADVP (AD 最))
									    (ADJP (JJ 重要)))
								      (NP (NN 市场)
									  (CC 与)
									  (NN 生产)
									  (NN 基地)))))))
					      (DEC 的)))
				      (NP (NN 台商))))
			  (VP (MSP 来)
			      (VP (VV 说)))))
	      (PU ，)
	      (NP-SBJ (DNP (NP (NN 池鱼之殃))
			   (DEG 的))
		      (NP (NN 冲击)))
	      (VP (ADVP (AD 同样))
		  (ADVP (AD 不))
		  (VP (VV 可)
		      (VP (VV 小觑))))) 
	  </parse>
	  <arg n="1">
	  池鱼之殃 的 冲击 
	  </arg>
	  <arg n="m" f="adv">
	  不 
	  </arg>
	  <arg n="m" f="adv">
	  同样 
	  </arg>
	  <arg n="m" f="adv">
	  *PRO* 对於 成千上万 家 、 *OP* *T*-1 仰赖 大陆 *PRO* 为 最 重要 市场 与 生产 基地 的 台商 来 说 
	  </arg>
	  <arg n="m" f="cnd">
	  大陆 若 是 因为 *PRO* 坚守 人民币 汇率 而 丧失 出口 竞争 优势 
	  </arg>
	  <V/>
	</example>
      </frame>
    </frameset>
  </verb>
