<!DOCTYPE verb SYSTEM "verb.dtd">
  <verb>
    <id> 支撑 </id>
    <frameset id="f1">
      <role argnum="0" argrole="buttress"/>
      <role argnum="1" argrole="thing buttressed"/>
      <frame>
	<mapping>
	  <V/>
	  <mapitem src="sbj" trg="arg0"/>
	  <mapitem src="npobj" trg="arg1"/>
	</mapping>
	<example>
	  <parse>
	  (IP (NP-SBJ (DNP (NP (NP (QP (CD 八))
				   (NP (NN 山)))
			       (NP (QP (CD 一))
				   (NP (NN 水)))
			       (QP (CD 一)
				   (CLP (M 分)))
			       (NP (NN 田)))
			   (DEG 的))
		      (NP-PN (NR 贵州)))
	      (PU ，)
	      (VP (VC 是)
		  (NP-PRD (NP-PN (NR 中国))
			  (ADJP (JJ 唯一))
			  (CP (WHNP-1 (-NONE- *OP*))
			      (CP (IP (NP-SBJ (-NONE- *T*-1))
				      (VP (VE 没有)
					  (IP-OBJ (NP-SBJ (NN 平原))
						  (VP (VV 支撑)))))
				  (DEC 的)))
			  (NP (NN 山区)
			      (NN 省份))))
	      (PU 。)) 
	  </parse>
	  <arg n="0">
	  平原 
	  </arg>
	  <V/>
	</example>
      </frame>
    </frameset>
  </verb> 
