<!DOCTYPE verb SYSTEM "verb.dtd">
  <verb>
    <id> 沐风 </id>
    <frameset id="f1">
      <role argnum="0" argrole="people described"/>
      <frame>
	<mapping>
	  <V/>
	  <mapitem src="sbj" trg="arg0"/>
	</mapping>
	<example>
	  <parse>
	  (IP (NP-SBJ (NP-PN (NR 中国))
		      (NP (NN 领导人)))
	      (VP (VP (VCD (VV 沐风)
			   (VV 栉雨)))
		  (PU ，)
		  (VP (VP (ADVP (AD 亲))
			  (VP (VV 临)
			      (NP-OBJ (NN 前线))))
		      (VP (VV 指挥))))) 
	  </parse>
	  <arg n="0">
	  中国 领导人 
	  </arg>
	  <V/>
	</example>
      </frame>
    </frameset>
  </verb>
