<!DOCTYPE verb SYSTEM "verb.dtd">
<verb>
  <id> 多变 </id>
  <frameset id="f1">
    <role argnum="0" argrole="entity described"/>
    <frame>
      <mapping>
	<V/>
	<mapitem src="sbj" trg="arg0"/>
      </mapping>
      <example>
	<parse>
	(IP (NP-TPC (DNP (NP (PN 他们))
			 (DEG 的))
		    (NP (NN 服装)
			(CC 与)
			(NN 织布)))
	    (NP-SBJ (NN 色彩))
	    (VP (VCD (VA 瑰丽)
		     (VA 多变)))) 
	</parse>
	<arg n="0" f="psr">
	他们 的 服装 与 织布 
	</arg>
	<arg n="0" f="pse">
	色彩 
	</arg>
	<V/>
      </example>
    </frame>
  </frameset>
</verb>
