<!DOCTYPE verb SYSTEM "verb.dtd">
<verb>
  <id> 纷歧 </id>
  <frameset id="f1">
    <role argnum="0" argrole="thing described"/>
    <frame>
      <mapping>
	<V/>
	<mapitem src="sbj" trg="arg0"/>
      </mapping>
      <example>
	<parse>
	(IP (NP-SBJ (-NONE- *pro*))
	    (VP (VV 创下)
		(NP-OBJ (CP-APP (IP (NP-TPC (NN 大法官))
				    (NP-SBJ (NN 意见))
				    (VP (VA 纷歧)))
				(DEC 的))
			(NP (NN 纪录))))) 
	</parse>
	<arg n="0" f="psr">
	大法官 
	</arg>
	<arg n="0" f="pse">
	意见 
	</arg>
	<V/>
      </example>
    </frame>
  </frameset>
</verb>
