<!DOCTYPE verb SYSTEM "verb.dtd">
<verb>
  <id> 不折不扣 </id>
  <frameset id="f1">
    <role argnum="0" argrole="entity described"/>
    <frame>
      <mapping>
	<V/>
	<mapitem src="sbj" trg="arg0"/>
      </mapping>
      <example>
	<parse>
	(IP (NP-SBJ (NP-APP (NN 父亲))
		    (NP-PN (NR 柯豪)))
	    (PU ，)
	    (VP (VP (NP-LOC (NP-PN (NR 浙江省))
			    (NP-PN (NR 之江)
				   (NN 大学))
			    (NP (NN 外文系)))
		    (VP (VV 毕业)))
		(PU ，)
		(VP (ADVP (AD 原))
		    (PP-LOC (P 在)
			    (NP-PN (NR 北一女中)))
		    (VP (VV 担任)
			(NP-OBJ (NN 英文)
				(NN 教席))))
		(PU ，)
		(VP (PP-LOC (P 在)
			    (LCP (NP (DNP (NP-PN (NR 隐地))
					  (DEG 的))
				     (NP (NN 眼)))
				 (LC 中)))
		    (ADVP (AD 却))
		    (VP (VC 是)
			(NP-PRD (QP (CLP (M 个)))
				(CP (WHNP-1 (-NONE- *OP*))
				    (CP (IP (NP-SBJ (-NONE- *T*-1))
					    (VP (VV 不折不扣)))
					(DEC 的)))
				(NP (NN 烂好人))))))) 
	</parse>
	<arg n="0">
	*T*-1 
	</arg>
	<V/>
      </example>
    </frame>
  </frameset>
</verb>
