<!DOCTYPE verb SYSTEM "verb.dtd">
  <verb>
    <id> 正典 </id>
    <frameset id="f1">
      <role argnum="0" argrole="entity described"/>
      <frame>
	<mapping>
	  <V/>
	  <mapitem src="sbj" trg="arg0"/>
	</mapping>
	<example>
	  <parse>
	  (IP (NP-SBJ (CP (WHNP-1 (-NONE- *OP*))
			  (CP (IP (NP-SBJ (-NONE- *T*-1))
				  (VP (ADVP (AD 最))
				      (VP (PU 『)
					  (VA 正典)
					  (PU 』))))
			      (DEC 的)))
		      (NP (NN 知识)
			  (NN 商品)))
	      (PU ，)
	      (VP (VV 应该)
		  (VP (VP (VV 发挥)
			  (NP-OBJ (NP (NN 知识))
				  (CP-APP (IP (NP-SBJ (NN 无形))
					      (VP (VV 胜)
						  (NP-OBJ (NN 有形))))
					  (DEC 的))
				  (NP (NN 威力))))
		      (PU ，)
		      (VP (VP (PP-MNR (P 用)
				      (NP (CP (WHNP-2 (-NONE- *OP*))
					      (CP (IP (NP-SBJ (-NONE- *T*-2))
						      (VP (ADVP (AD 很))
							  (VP (VA 低))))
						  (DEC 的)))
					  (NP (NN 成本))))
			      (ADVP (AD 大量))
			      (VP (VV 复制)))
			  (PU ，)
			  (VP (ADVP (AD 进而))
			      (VP (VV 赚取)
				  (NP-OBJ (ADJP (JJ 超额))
					  (NP (NN 利润))))))))) 
	  </parse>
	  <arg n="0">
	  *T*-1 
	  </arg>
	  <arg n="m" f="adv">
	  最 
	  </arg>
	  <V/>
	</example>
      </frame>
    </frameset>
  </verb>
